LICENSE
README.md
setup.py
src/address_name_system/__init__.py
src/address_name_system/address_name_system.py
src/address_name_system.egg-info/PKG-INFO
src/address_name_system.egg-info/SOURCES.txt
src/address_name_system.egg-info/dependency_links.txt
src/address_name_system.egg-info/entry_points.txt
src/address_name_system.egg-info/not-zip-safe
src/address_name_system.egg-info/requires.txt
src/address_name_system.egg-info/top_level.txt