Metadata-Version: 2.1
Name: address-name-system
Version: 0.2.2
Summary: Mapping Addresses to Dynamic IPs, Simplified
Home-page: https://github.com/Naruno/Address-Name-System
Author: Naruno Developers
Author-email: onur.atakan.ulusoy@naruno.org
License: MIT
Platform: UNKNOWN
Requires-Python: >= 3
